autolgbm/__init__.py
autolgbm/api.py
autolgbm/autolgbm.py
autolgbm/enums.py
autolgbm/logger.py
autolgbm/metrics.py
autolgbm/params.py
autolgbm/predict.py
autolgbm/schemas.py
autolgbm/utils.py
autolgbm/cli/__init__.py
autolgbm/cli/autolgbm.py
autolgbm/cli/predict.py
autolgbm/cli/serve.py
autolgbm/cli/train.py
autolgbm-0.0.3.dist-info/LICENSE
autolgbm-0.0.3.dist-info/METADATA
autolgbm-0.0.3.dist-info/WHEEL
autolgbm-0.0.3.dist-info/entry_points.txt
autolgbm-0.0.3.dist-info/top_level.txt
autolgbm-0.0.3.dist-info/RECORD
